vexmessage/__init__.py
vexmessage-0.4.0.dist-info/DESCRIPTION.rst
vexmessage-0.4.0.dist-info/METADATA
vexmessage-0.4.0.dist-info/RECORD
vexmessage-0.4.0.dist-info/WHEEL
vexmessage-0.4.0.dist-info/metadata.json
vexmessage-0.4.0.dist-info/top_level.txt
